LICENSE
MANIFEST.in
README.md
setup.py
bart2/AUCcalc.py
bart2/EnhancerIdentifier.py
bart2/IOparser.py
bart2/OptValidator.py
bart2/RPRegress.py
bart2/ReadCount.py
bart2/StatTest.py
bart2/__init__.py
bart2/bart.conf
bart2/main.py
bart2/score_on_UDHS.py
bart2.egg-info/PKG-INFO
bart2.egg-info/SOURCES.txt
bart2.egg-info/dependency_links.txt
bart2.egg-info/requires.txt
bart2.egg-info/top_level.txt
bin/bart2