Metadata-Version: 1.1
Name: bart2
Version: 2.0
Summary: Binding Analysis for Regulatory Transcription Factors of Genes - Revised version
Home-page: https://github.com/marvinquiet/bart2
Author: Zhanjia Wang, Wenjing Ma
Author-email: zhenjia@virginia.edu, wm9tr@virginia.edu
License: UNKNOWN
Platform: UNKNOWN
Classifier: Development Status :: 4 - Beta
Classifier: Environment :: Console
Classifier: Intended Audience :: Science/Research
Classifier: Operating System :: MacOS :: MacOS X
Classifier: Operating System :: POSIX
Classifier: Topic :: Scientific/Engineering :: Bio-Informatics
Classifier: Programming Language :: Python
